.pypirc
MANIFEST.in
README.rst
bootstrap.py
buildout.cfg
distribute-0.6.24.tar.gz
setup.py
collective/__init__.py
collective.rip.egg-info/PKG-INFO
collective.rip.egg-info/SOURCES.txt
collective.rip.egg-info/dependency_links.txt
collective.rip.egg-info/entry_points.txt
collective.rip.egg-info/namespace_packages.txt
collective.rip.egg-info/not-zip-safe
collective.rip.egg-info/requires.txt
collective.rip.egg-info/top_level.txt
collective/rip/__init__.py
collective/rip/configure.zcml
collective/rip/browser/__init__.py
collective/rip/browser/configure.zcml
collective/rip/browser/rip.pt
collective/rip/browser/rip.py
collective/rip/profiles/default/controlpanel.xml
docs/HISTORY.txt
docs/LICENSE.GPL
docs/LICENSE.txt