Metadata-Version: 1.0
Name: collective.rip
Version: 1.3.0
Summary: Edit CSS and JavaScript in Plone control panel
Home-page: http://collective.github.com/collective.rip/
Author: Alex Clark
Author-email: aclark@aclark.net
License: ZPL
Keywords: css html javascript plone theme
Platform: UNKNOWN
Classifier: Framework :: Plone
Classifier: Programming Language :: Python
